[
  {
    "id": "1",
    "teams": { "home": "Real Madrid", "away": "Barcelona" },
    "status": "live",
    "score": { "home": 2, "away": 1 },
    "startTime": "2025-05-28T18:00:00Z",
    "league": "La Liga"
  },
  {
    "id": "2",
    "teams": { "home": "Man City", "away": "Liverpool" },
    "status": "finished",
    "score": { "home": 3, "away": 2 },
    "startTime": "2025-05-27T15:00:00Z",
    "league": "Premier League"
  },
  {
    "id": "3",
    "teams": { "home": "Juventus", "away": "AC Milan" },
    "status": "upcoming",
    "score": { "home": 0, "away": 0 },
    "startTime": "2025-05-30T20:00:00Z",
    "league": "Serie A"
  }
]